swisspair/libswisspair.dylib
swisspair/interface.py
swisspair/libgmpwrap.dylib
swisspair/__init__.py
swisspair/libmincostpmatch.dylib
swisspair/_swisspair.cpython-39-darwin.so
swisspair/.dylibs/libgmp.10.dylib
swisspair-0.2.1.dist-info/RECORD
swisspair-0.2.1.dist-info/WHEEL
swisspair-0.2.1.dist-info/METADATA
swisspair-0.2.1.dist-info/licenses/LICENSE
