Metadata-Version: 2.1
Name: swisspair
Version: 0.2.1
Summary: Python bindings for Swiss pairing algorithm for (not only) Magic: The Gathering.
Requires-Python: >=3.9
Provides-Extra: test
Requires-Dist: pytest; extra == "test"
